amulet/io/__init__.py
amulet/io/_version.py
amulet/io/amulet_ioConfig.cmake
amulet/io/binary_reader.hpp
amulet/io/binary_writer.hpp
amulet/io/py.typed
amulet_io-1.0.1.dist-info/METADATA
amulet_io-1.0.1.dist-info/WHEEL
amulet_io-1.0.1.dist-info/top_level.txt
amulet_io-1.0.1.dist-info/RECORD
