Metadata-Version: 2.4
Name: amulet-io
Version: 1.0.1
Summary: A tiny C++ header-only binary reader and writer library.
Author: James Clare
Project-URL: Homepage, https://www.amuletmc.com
Project-URL: Repository, https://github.com/Amulet-Team/Amulet-IO
Project-URL: Issues, https://github.com/Amulet-Team/Amulet-IO/issues
Classifier: Programming Language :: Python :: 3
Classifier: Operating System :: OS Independent
Requires-Python: >=3.11
Provides-Extra: dev
Requires-Dist: setuptools>=42; extra == "dev"
Requires-Dist: versioneer; extra == "dev"
Requires-Dist: wheel; extra == "dev"
Requires-Dist: pybind11[global]==2.13.6; extra == "dev"
Requires-Dist: amulet-test-utils~=1.0; extra == "dev"
Requires-Dist: black>=22.3; extra == "dev"
